[
  {
    "TimestampMs": 0,
    "Packet": "BAIIgICAgAA="
  },
  {
    "TimestampMs": 123,
    "Packet": "BAAIgICAgAA="
  },
  {
    "TimestampMs": 311,
    "Packet": "AAAIgICAgAA="
  },
  {
    "TimestampMs": 818,
    "Packet": "AgAIgICAgAA="
  },
  {
    "TimestampMs": 926,
    "Packet": "AAAIgICAgAA="
  },
  {
    "TimestampMs": 1296,
    "Packet": "AAAIgICAVQA="
  },
  {
    "TimestampMs": 1301,
    "Packet": "AAAIgIB3PAA="
  },
  {
    "TimestampMs": 1313,
    "Packet": "AAAIgIB2IQA="
  },
  {
    "TimestampMs": 1327,
    "Packet": "AAAIgIB2AAA="
  },
  {
    "TimestampMs": 1343,
    "Packet": "AAAIgIB1AAA="
  },
  {
    "TimestampMs": 1374,
    "Packet": "AAAIgICABAA="
  },
  {
    "TimestampMs": 1379,
    "Packet": "AAAIgICAHAA="
  },
  {
    "TimestampMs": 1391,
    "Packet": "AAAIgICAMQA="
  },
  {
    "TimestampMs": 1404,
    "Packet": "AAAIgICASwA="
  },
  {
    "TimestampMs": 1409,
    "Packet": "AAAIgICAXAA="
  },
  {
    "TimestampMs": 1419,
    "Packet": "AAAIgICAgAA="
  },
  {
    "TimestampMs": 1487,
    "Packet": "AAAIgICAbAA="
  },
  {
    "TimestampMs": 1496,
    "Packet": "AAAIgICAVgA="
  },
  {
    "TimestampMs": 1499,
    "Packet": "AAAIgICAPgA="
  },
  {
    "TimestampMs": 1512,
    "Packet": "AAAIgICAKAA="
  },
  {
    "TimestampMs": 1517,
    "Packet": "AAAIgICAGQA="
  },
  {
    "TimestampMs": 1529,
    "Packet": "AAAIgICAEQA="
  },
  {
    "TimestampMs": 1543,
    "Packet": "AAAIgICKEQA="
  },
  {
    "TimestampMs": 1558,
    "Packet": "AAAIgICOEwA="
  },
  {
    "TimestampMs": 1559,
    "Packet": "AAAIgICQFwA="
  },
  {
    "TimestampMs": 1573,
    "Packet": "AAAIgICSHwA="
  },
  {
    "TimestampMs": 1577,
    "Packet": "AAAIgICRLQA="
  },
  {
    "TimestampMs": 1589,
    "Packet": "AAAIgICMTgA="
  },
  {
    "TimestampMs": 1604,
    "Packet": "AAAIgICAXgA="
  },
  {
    "TimestampMs": 1607,
    "Packet": "AAAIgICAgAA="
  },
  {
    "TimestampMs": 1666,
    "Packet": "AAAIgICAWgA="
  },
  {
    "TimestampMs": 1681,
    "Packet": "AAAIgICAIwA="
  },
  {
    "TimestampMs": 1685,
    "Packet": "AAAIgICABQA="
  },
  {
    "TimestampMs": 1697,
    "Packet": "AAAIgICAAAA="
  },
  {
    "TimestampMs": 1727,
    "Packet": "AAAIgICHAAA="
  },
  {
    "TimestampMs": 1743,
    "Packet": "AAAIgICVAAA="
  },
  {
    "TimestampMs": 1751,
    "Packet": "AAAIgICZDgA="
  },
  {
    "TimestampMs": 1758,
    "Packet": "AAAIgICYHgA="
  },
  {
    "TimestampMs": 1774,
    "Packet": "AAAIgICYMQA="
  },
  {
    "TimestampMs": 1775,
    "Packet": "AAAIgICWRAA="
  },
  {
    "TimestampMs": 1789,
    "Packet": "AAAIgICVUgA="
  },
  {
    "TimestampMs": 1793,
    "Packet": "AAAIgICUWAA="
  },
  {
    "TimestampMs": 1805,
    "Packet": "AAAIgICUWgA="
  },
  {
    "TimestampMs": 1821,
    "Packet": "AAAIgICUXQA="
  },
  {
    "TimestampMs": 1823,
    "Packet": "AAAIgICSXQA="
  },
  {
    "TimestampMs": 1836,
    "Packet": "AAAIgICOXAA="
  },
  {
    "TimestampMs": 1841,
    "Packet": "AAAIgICKXQA="
  },
  {
    "TimestampMs": 1852,
    "Packet": "AAAIgICAXgA="
  },
  {
    "TimestampMs": 1871,
    "Packet": "AAAIgICAXQA="
  },
  {
    "TimestampMs": 1883,
    "Packet": "AAAIgIB2WwA="
  },
  {
    "TimestampMs": 1889,
    "Packet": "AAAIgIBzVQA="
  },
  {
    "TimestampMs": 1898,
    "Packet": "AAAIgIByTgA="
  },
  {
    "TimestampMs": 1901,
    "Packet": "AAAIgIBwRAA="
  },
  {
    "TimestampMs": 1914,
    "Packet": "AAAIgIBvPQA="
  },
  {
    "TimestampMs": 1919,
    "Packet": "AAAIgIBvPAA="
  },
  {
    "TimestampMs": 1949,
    "Packet": "AAAIgIBzPQA="
  },
  {
    "TimestampMs": 1961,
    "Packet": "AAAIgIB2QAA="
  },
  {
    "TimestampMs": 1967,
    "Packet": "AAAIgICASAA="
  },
  {
    "TimestampMs": 1975,
    "Packet": "AAAIgICAVAA="
  },
  {
    "TimestampMs": 1979,
    "Packet": "AAAIgICAXAA="
  },
  {
    "TimestampMs": 1991,
    "Packet": "AAAIgICAaAA="
  },
  {
    "TimestampMs": 1997,
    "Packet": "AAAIgICAgAA="
  },
  {
    "TimestampMs": 2501,
    "Packet": "AAAIaoCAgAA="
  },
  {
    "TimestampMs": 2515,
    "Packet": "AAAIZ4CAgAA="
  },
  {
    "TimestampMs": 2530,
    "Packet": "AAAIZYCAgAA="
  },
  {
    "TimestampMs": 2531,
    "Packet": "AAAIZIeAgAA="
  },
  {
    "TimestampMs": 2545,
    "Packet": "AAAIY4iAgAA="
  },
  {
    "TimestampMs": 2549,
    "Packet": "AAAIYYiAgAA="
  },
  {
    "TimestampMs": 2561,
    "Packet": "AAAIXoiAgAA="
  },
  {
    "TimestampMs": 2576,
    "Packet": "AAAIWYqAgAA="
  },
  {
    "TimestampMs": 2579,
    "Packet": "AAAIWIqAgAA="
  },
  {
    "TimestampMs": 2597,
    "Packet": "AAAIV4uAgAA="
  },
  {
    "TimestampMs": 2623,
    "Packet": "AAAIV4yAgAA="
  },
  {
    "TimestampMs": 2685,
    "Packet": "AAAIV42AgAA="
  },
  {
    "TimestampMs": 2687,
    "Packet": "AAAIV4yAgAA="
  },
  {
    "TimestampMs": 2693,
    "Packet": "AAAIV42AgAA="
  },
  {
    "TimestampMs": 2809,
    "Packet": "AAAIV4yAgAA="
  },
  {
    "TimestampMs": 2823,
    "Packet": "AAAIV42AgAA="
  },
  {
    "TimestampMs": 2854,
    "Packet": "AAAIV4yAgAA="
  },
  {
    "TimestampMs": 2855,
    "Packet": "AAAIVoyAgAA="
  },
  {
    "TimestampMs": 2885,
    "Packet": "AAAIVo2AgAA="
  },
  {
    "TimestampMs": 2900,
    "Packet": "AAAIVo6AgAA="
  },
  {
    "TimestampMs": 2963,
    "Packet": "AAAIVY+AgAA="
  },
  {
    "TimestampMs": 3001,
    "Packet": "AAAIVI+AgAA="
  },
  {
    "TimestampMs": 3009,
    "Packet": "AAAIUY+AgAA="
  },
  {
    "TimestampMs": 3025,
    "Packet": "AAAISpCAgAA="
  },
  {
    "TimestampMs": 3025,
    "Packet": "AAAIRJCAgAA="
  },
  {
    "TimestampMs": 3040,
    "Packet": "AAAIQZCAgAA="
  },
  {
    "TimestampMs": 3041,
    "Packet": "AAAIPo+AgAA="
  },
  {
    "TimestampMs": 3071,
    "Packet": "AAAIPo6AgAA="
  },
  {
    "TimestampMs": 3086,
    "Packet": "AAAIPoyAgAA="
  },
  {
    "TimestampMs": 3091,
    "Packet": "AAAIPoqAgAA="
  },
  {
    "TimestampMs": 3102,
    "Packet": "AAAIP4qAgAA="
  },
  {
    "TimestampMs": 3103,
    "Packet": "AAAIRYqAgAA="
  },
  {
    "TimestampMs": 3117,
    "Packet": "AAAITYuAgAA="
  },
  {
    "TimestampMs": 3133,
    "Packet": "AAAIU4qAgAA="
  },
  {
    "TimestampMs": 3225,
    "Packet": "AAAIVImAgAA="
  },
  {
    "TimestampMs": 3240,
    "Packet": "AAAIWYiAgAA="
  },
  {
    "TimestampMs": 3241,
    "Packet": "AAAIXoiAgAA="
  },
  {
    "TimestampMs": 3256,
    "Packet": "AAAIYoiAgAA="
  },
  {
    "TimestampMs": 3271,
    "Packet": "AAAIZYeAgAA="
  },
  {
    "TimestampMs": 3367,
    "Packet": "AAAIZYCAgAA="
  },
  {
    "TimestampMs": 3415,
    "Packet": "AAAIaYCAgAA="
  },
  {
    "TimestampMs": 3427,
    "Packet": "AAAIgICAgAA="
  },
  {
    "TimestampMs": 3949,
    "Packet": "AAQIgICAgAA="
  },
  {
    "TimestampMs": 4033,
    "Packet": "AAAIgICAgAA="
  },
  {
    "TimestampMs": 4475,
    "Packet": "AAQIgICAgAA="
  },
  {
    "TimestampMs": 4568,
    "Packet": "AAAIgICAgAA="
  },
  {
    "TimestampMs": 4633,
    "Packet": "AAQIgICAgAA="
  },
  {
    "TimestampMs": 4737,
    "Packet": "AAAIgICAgAA="
  },
  {
    "TimestampMs": 4801,
    "Packet": "AAQIgICAgAA="
  },
  {
    "TimestampMs": 4891,
    "Packet": "AAAIgICAgAA="
  },
  {
    "TimestampMs": 4987,
    "Packet": "AAQIgICAgAA="
  },
  {
    "TimestampMs": 5047,
    "Packet": "AAAIgICAgAA="
  },
  {
    "TimestampMs": 11720,
    "Packet": "BAAIgICAgAA="
  },
  {
    "TimestampMs": 11875,
    "Packet": "AAAIgICAgAA="
  },
  {
    "TimestampMs": 12187,
    "Packet": "BAAIgICAgAA="
  }
]